CHANGES
LICENSE
MANIFEST.in
README.rst
setup.py
cmsplugin_rt/__init__.py
cmsplugin_rt.egg-info/PKG-INFO
cmsplugin_rt.egg-info/SOURCES.txt
cmsplugin_rt.egg-info/dependency_links.txt
cmsplugin_rt.egg-info/not-zip-safe
cmsplugin_rt.egg-info/top_level.txt
cmsplugin_rt/button/__init__.py
cmsplugin_rt/button/cms_plugins.py
cmsplugin_rt/button/forms.py
cmsplugin_rt/button/models.py
cmsplugin_rt/button/migrations/0001_initial.py
cmsplugin_rt/button/migrations/0002_auto__chg_field_buttonpluginmodel_button_link.py
cmsplugin_rt/button/migrations/__init__.py
cmsplugin_rt/button/templates/button_plugin.html
cmsplugin_rt/button/templatetags/__init__.py
cmsplugin_rt/button/templatetags/allow_special.py
cmsplugin_rt/button_appstore/__init__.py
cmsplugin_rt/button_appstore/cms_plugins.py
cmsplugin_rt/button_appstore/models.py
cmsplugin_rt/button_appstore/migrations/0001_initial.py
cmsplugin_rt/button_appstore/migrations/__init__.py
cmsplugin_rt/button_appstore/templates/button_appstore_plugin.html
cmsplugin_rt/facebook_button/__init__.py
cmsplugin_rt/facebook_button/cms_plugins.py
cmsplugin_rt/facebook_button/models.py
cmsplugin_rt/facebook_button/migrations/0001_initial.py
cmsplugin_rt/facebook_button/migrations/__init__.py
cmsplugin_rt/facebook_button/templates/facebook_button_plugin.html
cmsplugin_rt/google_analytics/__init__.py
cmsplugin_rt/google_analytics/cms_plugins.py
cmsplugin_rt/google_analytics/models.py
cmsplugin_rt/google_analytics/migrations/0001_initial.py
cmsplugin_rt/google_analytics/migrations/__init__.py
cmsplugin_rt/google_analytics/templates/google_analytics_plugin.html
cmsplugin_rt/google_font/__init__.py
cmsplugin_rt/google_font/cms_plugins.py
cmsplugin_rt/google_font/models.py
cmsplugin_rt/google_font/migrations/0001_initial.py
cmsplugin_rt/google_font/migrations/__init__.py
cmsplugin_rt/google_font/templates/google_font_plugin.html
cmsplugin_rt/hbar/__init__.py
cmsplugin_rt/hbar/cms_plugins.py
cmsplugin_rt/hbar/models.py
cmsplugin_rt/hbar/migrations/0001_initial.py
cmsplugin_rt/hbar/migrations/__init__.py
cmsplugin_rt/hbar/templates/hbar_plugin.html
cmsplugin_rt/mailchimp_form/__init__.py
cmsplugin_rt/mailchimp_form/cms_plugins.py
