Metadata-Version: 1.1
Name: cmsplugin-rt
Version: 0.5.1
Summary: This package contains a number of basic plugins to kick start your DjangoCMS project, such as Twitter Bootstrap navbar and buttons, Facebook and Twitter buttons, a Style Modifier, Google Analytics tracking code, Google fonts, meta tags and resizable pictures.
Home-page: https://github.com/RacingTadpole/cmsplugin-rt
Author: Art Street
Author-email: art@racingtadpole.com
License: BSD License
Keywords: button meta twitter bootstrap style modifier racing tadpole
Platform: UNKNOWN
Classifier: Environment :: Web Environment
Classifier: Framework :: Django
Classifier: Intended Audience :: Developers
Classifier: License :: OSI Approved :: BSD License
Classifier: Operating System :: OS Independent
Classifier: Programming Language :: Python
Classifier: Programming Language :: Python :: 2.7
Classifier: Topic :: Internet :: WWW/HTTP
Classifier: Topic :: Internet :: WWW/HTTP :: Dynamic Content
